LICENSE
MANIFEST.in
README.md
setup.py
django_unisender.egg-info/PKG-INFO
django_unisender.egg-info/SOURCES.txt
django_unisender.egg-info/dependency_links.txt
django_unisender.egg-info/not-zip-safe
django_unisender.egg-info/requires.txt
django_unisender.egg-info/top_level.txt
unisender/__init__.py
unisender/admin.py
unisender/error_codes.py
unisender/managers.py
unisender/models.py
unisender/settings.py
unisender/unisender_urls.py
unisender/views.py
unisender/migrations/0001_initial.py
unisender/migrations/0001_initial.pyc
unisender/migrations/0002_auto__chg_field_subscriber_double_optin.py
unisender/migrations/0002_auto__chg_field_subscriber_double_optin.pyc
unisender/migrations/0003_auto__chg_field_emailmessage_tag__chg_field_emailmessage_list_id.py
unisender/migrations/0003_auto__chg_field_emailmessage_tag__chg_field_emailmessage_list_id.pyc
unisender/migrations/0004_auto__chg_field_campaign_email_message.py
unisender/migrations/0004_auto__chg_field_campaign_email_message.pyc
unisender/migrations/0005_auto__chg_field_campaign_name.py
unisender/migrations/0005_auto__chg_field_campaign_name.pyc
unisender/migrations/0006_auto__add_attachment.py
unisender/migrations/0006_auto__add_attachment.pyc
unisender/migrations/0007_auto__add_visitedlink.py
unisender/migrations/0007_auto__add_visitedlink.pyc
unisender/migrations/0008_auto__add_optinemail.py
unisender/migrations/0008_auto__add_optinemail.pyc
unisender/migrations/__init__.py
unisender/migrations/__init__.pyc
unisender/templates/unisender/admin/change_campaign.html
unisender/templates/unisender/admin/change_campaign_list.html
unisender/templates/unisender/admin/change_emailmessage.html
unisender/templates/unisender/admin/change_emailmessage_list.html
unisender/templates/unisender/admin/change_field_list.html
unisender/templates/unisender/admin/change_subscriber_list_detail.html
unisender/templates/unisender/admin/change_subscriber_list_list.html
unisender/templates/unisender/admin/change_tag_list.html
unisender/tests/__init__.py
unisender/tests/__init__.pyc
unisender/tests/admin.py
unisender/tests/admin.pyc
unisender/tests/cabinet_links.py
unisender/tests/cabinet_links.pyc
unisender/tests/managers.py
unisender/tests/managers.pyc
